[
  { "id": "rf9hb", "url": "https://qu.ax/ZjszW.mp4" },
  { "id": "AOCoH", "url": "https://qu.ax/VCsJL.mp4" },
  { "id": "FxHbC", "url": "https://qu.ax/vTNmu.mp4" },
  { "id": "7YvjN", "url": "https://qu.ax/tZZXl.mp4" },
  { "id": "rtyQE", "url": "https://qu.ax/WrcOq.mp4" },
  { "id": "87VrT", "url": "https://qu.ax/fhTMQ.mp4" },
  { "id": "kWRrO", "url": "https://qu.ax/VdQby.mp4" },
  { "id": "QHPNZ", "url": "https://qu.ax/WAZdz.mp4" },
  { "id": "PKKe1", "url": "https://qu.ax/SpCCa.mov" },
  { "id": "nB72n", "url": "https://qu.ax/dqehS.mov" },
  { "id": "hBFtC", "url": "https://qu.ax/WkTAo.mov" },
  { "id": "rd4Ux", "url": "https://qu.ax/kjjyz.mov" },
  { "id": "zPFCl", "url": "https://qu.ax/DSizT.mov" },
  { "id": "OJoEk", "url": "https://qu.ax/EpxJN.mov" },
  { "id": "au1oF", "url": "https://qu.ax/PoCNm.mov" },
  { "id": "1yTOA", "url": "https://qu.ax/bnNWk.mov" },
  { "id": "uMNZo", "url": "https://qu.ax/AcZnW.mov" }
]